.coveragerc
.gitignore
AUTHORS.rst
CHANGELOG.rst
LICENSE.txt
Pipfile
Pipfile.lock
README.md
requirements.txt
setup.cfg
setup.py
docs/Makefile
docs/authors.rst
docs/changelog.rst
docs/conf.py
docs/index.rst
docs/license.rst
docs/_static/.gitignore
src/kevweatherone/__init__.py
src/kevweatherone/index.py
src/kevweatherone/skeleton.py
src/kevweatherone/theweather.py
src/kevweatherone.egg-info/PKG-INFO
src/kevweatherone.egg-info/SOURCES.txt
src/kevweatherone.egg-info/dependency_links.txt
src/kevweatherone.egg-info/entry_points.txt
src/kevweatherone.egg-info/not-zip-safe
src/kevweatherone.egg-info/requires.txt
src/kevweatherone.egg-info/top_level.txt
tests/conftest.py
tests/test_skeleton.py