Metadata-Version: 2.1
Name: kevweatherone
Version: 0.2.0
Summary: Add a short description here!
Home-page: https://github.com/kevbaker/kevweatherone
Author: Kevin Baker
Author-email: kbaker@atomeq.com
License: mit
Platform: any
Classifier: Development Status :: 4 - Beta
Classifier: Programming Language :: Python
Provides-Extra: testing
